lsml-0.0.1.dist-info/RECORD
lsml-0.0.1.dist-info/top_level.txt
lsml-0.0.1.dist-info/METADATA
lsml-0.0.1.dist-info/WHEEL
lsml/visualize.py
lsml/__init__.py
lsml/score_functions.py
lsml/_version.py
lsml/data/__init__.py
lsml/data/dim2/__init__.py
lsml/data/dim2/gestalt_triangle.py
lsml/data/dim2/hamburger.py
lsml/data/dim3/__init__.py
lsml/data/dim3/hamburger.py
lsml/util/on_iterate.py
lsml/util/masked_gradient.cpython-37m-x86_64-linux-gnu.so
lsml/util/balance_mask.py
lsml/util/__init__.py
lsml/util/distance_transform.py
lsml/util/test/test_distance_transform.py
lsml/util/test/__init__.py
lsml/util/test/test_balance_mask.py
lsml/feature/base_feature.py
lsml/feature/feature_map.py
lsml/feature/__init__.py
lsml/feature/test/test_feature_map.py
lsml/feature/test/test_base_feature.py
lsml/feature/test/__init__.py
lsml/feature/provided/image.py
lsml/feature/provided/__init__.py
lsml/feature/provided/shape.py
lsml/feature/provided/test/test_image.py
lsml/feature/provided/test/test_shape.py
lsml/feature/provided/test/__init__.py
lsml/initializer/seed.py
lsml/initializer/__init__.py
lsml/initializer/initializer_base.py
lsml/initializer/test/test_seed.py
lsml/initializer/test/__init__.py
lsml/initializer/test/test_initializer_base.py
lsml/initializer/provided/ray_trim.py
lsml/initializer/provided/__init__.py
lsml/initializer/provided/ball.py
lsml/initializer/provided/threshold.py
lsml/initializer/provided/test/test_ball.py
lsml/initializer/provided/test/__init__.py
lsml/initializer/provided/test/test_threshold.py
lsml/initializer/provided/util/__init__.py
lsml/initializer/provided/util/test/__init__.py
lsml/gradient/masked_gradient.py
lsml/gradient/__init__.py
lsml/gradient/test/test_masked_gradient.py
lsml/gradient/test/__init__.py
lsml/core/model.py
lsml/core/fit_job_handler.py
lsml/core/exception.py
lsml/core/datasets_handler.py
lsml/core/__init__.py
lsml/core/temporary_data_handler.py
lsml/core/test/__init__.py
lsml/core/test/test_datasets_handler.py
